ai_text_ap/__init__.py
ai_text_ap/core.py
ai_text_ap-0.1.0.dist-info/licenses/LICENSE
ai_text_ap-0.1.0.dist-info/METADATA
ai_text_ap-0.1.0.dist-info/WHEEL
ai_text_ap-0.1.0.dist-info/top_level.txt
ai_text_ap-0.1.0.dist-info/RECORD
