Metadata-Version: 2.4
Name: ai_text_ap
Version: 0.1.0
Summary: Simple AI text helpers (example) - ai_text_ap
Author: Anaswara
License: MIT
Classifier: Programming Language :: Python :: 3
Classifier: License :: OSI Approved :: MIT License
Requires-Python: >=3.8
License-File: LICENSE
Requires-Dist: requests>=2.28.0
Dynamic: author
Dynamic: classifier
Dynamic: description
Dynamic: description-content-type
Dynamic: license
Dynamic: license-file
Dynamic: requires-dist
Dynamic: requires-python
Dynamic: summary
